dataframe_short/__init__.py
dataframe_short/cant_use_ds.py
dataframe_short/convert_types.py
dataframe_short/dataframe_test.py
dataframe_short/display.py
dataframe_short/fix_bug_ds.py
dataframe_short/func_24_Feb.py
dataframe_short/lib02_dataframe.py
dataframe_short/move_column.py
dataframe_short/sandbox1_ds.py
dataframe_short/utils_ds.py
dataframe_short-0.1.12.dist-info/LICENSE
dataframe_short-0.1.12.dist-info/METADATA
dataframe_short-0.1.12.dist-info/WHEEL
dataframe_short-0.1.12.dist-info/top_level.txt
dataframe_short-0.1.12.dist-info/RECORD
