Metadata-Version: 2.1
Name: dataframe_short
Version: 0.1.12
Summary: package build on top of pandas and add more convient functionality. Make your code short and easy to read
Home-page: https://github.com/DearNorathee/dataframe_short
Author: Dear Norathee
Author-email: noratee5@hotmail.com
License: MIT
License-File: LICENSE
Requires-Dist: pandas
Requires-Dist: os-toolkit >=0.1.2
Requires-Dist: py-string-tool >=0.1.4
Requires-Dist: datatable
Requires-Dist: polars
Requires-Dist: python-wizard >=0.1.3
Requires-Dist: pyxlsb
Requires-Dist: inspect-py >=0.1.2
